galr/__init__.py
galr/galr.py
galr-0.1.2.dist-info/licenses/LICENSE
galr-0.1.2.dist-info/METADATA
galr-0.1.2.dist-info/WHEEL
galr-0.1.2.dist-info/top_level.txt
galr-0.1.2.dist-info/RECORD
